oath/__init__.py
oath/_hotp.py
oath/_ocra.py
oath/_totp.py
oath/_utils.py
oath/google_authenticator.py
oath-1.4.4.dist-info/COPYING
oath-1.4.4.dist-info/METADATA
oath-1.4.4.dist-info/WHEEL
oath-1.4.4.dist-info/top_level.txt
oath-1.4.4.dist-info/RECORD
