Metadata-Version: 1.1
Name: oath
Version: 1.4.4
Summary: Python implementation of the three main OATH specifications: HOTP, TOTP and OCRA
Home-page: https://github.com/bdauvergne/python-oath
Author: Benjamin Dauvergne
Author-email: bdauvergne@entrouvert.com
License: BSD 3-clause
Platform: UNKNOWN
Classifier: Development Status :: 5 - Production/Stable
Classifier: Intended Audience :: Developers
Classifier: License :: OSI Approved :: MIT License
Classifier: Operating System :: OS Independent
Classifier: Programming Language :: Python
Classifier: Programming Language :: Python :: 2
Classifier: Programming Language :: Python :: 3
Classifier: Topic :: Security
Classifier: Topic :: Security :: Cryptography
